./Dockerfile
./README.md
./mcp_server.py
./pyproject.toml
./smithery.yaml
cite_agent_mcp-0.1.0.dist-info/METADATA
cite_agent_mcp-0.1.0.dist-info/WHEEL
cite_agent_mcp-0.1.0.dist-info/entry_points.txt
cite_agent_mcp-0.1.0.dist-info/RECORD
