Metadata-Version: 2.4
Name: cite-agent-mcp
Version: 0.1.0
Summary: Professional AI Research Assistant MCP Server with Citations
Author-email: Christopher Ongko <chris@cite-finance.io>
Requires-Python: >=3.10
Requires-Dist: cite-agent>=2.0.0
Requires-Dist: httpx>=0.20.0
Requires-Dist: mcp>=0.1.0
Requires-Dist: starlette>=0.20.0
Requires-Dist: uvicorn>=0.20.0
